odoo9_addon_l10n_cn_hr_payroll-9.0.2.0.0.99.dev23-py2.7-nspkg.pth
odoo9_addon_l10n_cn_hr_payroll-9.0.2.0.0.99.dev23.dist-info/DESCRIPTION.rst
odoo9_addon_l10n_cn_hr_payroll-9.0.2.0.0.99.dev23.dist-info/METADATA
odoo9_addon_l10n_cn_hr_payroll-9.0.2.0.0.99.dev23.dist-info/RECORD
odoo9_addon_l10n_cn_hr_payroll-9.0.2.0.0.99.dev23.dist-info/WHEEL
odoo9_addon_l10n_cn_hr_payroll-9.0.2.0.0.99.dev23.dist-info/metadata.json
odoo9_addon_l10n_cn_hr_payroll-9.0.2.0.0.99.dev23.dist-info/namespace_packages.txt
odoo9_addon_l10n_cn_hr_payroll-9.0.2.0.0.99.dev23.dist-info/top_level.txt
odoo_addons/l10n_cn_hr_payroll/README.rst
odoo_addons/l10n_cn_hr_payroll/__init__.py
odoo_addons/l10n_cn_hr_payroll/__openerp__.py
odoo_addons/l10n_cn_hr_payroll/data/leave_type_data.xml
odoo_addons/l10n_cn_hr_payroll/data/salary_rule_basic.xml
odoo_addons/l10n_cn_hr_payroll/data/salary_rule_category.xml
odoo_addons/l10n_cn_hr_payroll/data/salary_rule_nj1.xml
odoo_addons/l10n_cn_hr_payroll/data/salary_rule_sh1.xml
odoo_addons/l10n_cn_hr_payroll/data/salary_rule_sh2.xml
odoo_addons/l10n_cn_hr_payroll/data/salary_rule_sh3.xml
odoo_addons/l10n_cn_hr_payroll/data/salary_rule_sh4.xml
odoo_addons/l10n_cn_hr_payroll/data/salary_rule_sz1.xml
odoo_addons/l10n_cn_hr_payroll/data/salary_rule_sz2.xml
odoo_addons/l10n_cn_hr_payroll/data/salary_rule_sz3.xml
odoo_addons/l10n_cn_hr_payroll/data/salary_rule_sz4.xml
odoo_addons/l10n_cn_hr_payroll/i18n/zh_CN.po
odoo_addons/l10n_cn_hr_payroll/models/__init__.py
odoo_addons/l10n_cn_hr_payroll/models/l10n_cn_hr_payroll.py
odoo_addons/l10n_cn_hr_payroll/static/description/icon.png
odoo_addons/l10n_cn_hr_payroll/tests/__init__.py
odoo_addons/l10n_cn_hr_payroll/tests/test_payroll.py
odoo_addons/l10n_cn_hr_payroll/views/l10n_cn_hr_payroll_view.xml
odoo_addons/l10n_cn_hr_payroll/views/report_payslip.xml
